{
  "session_id": "94b72d0b-b36f-4650-87b0-ecd8c8e13a98",
  "items": [],
  "evidence": [
    {
      "kind": "argo",
      "level": "live deployment/Argo",
      "value": "healthy-synced"
    },
    {
      "kind": "k8s",
      "level": "live deployment/Argo",
      "value": "pod-succeeded"
    },
    {
      "kind": "runtime",
      "level": "blocked",
      "value": "failed-or-degraded"
    },
    {
      "kind": "artifact",
      "level": "focused CI-like",
      "value": "marketing-gitops-promotion-main-e8f02e8e697a.zip"
    },
    {
      "kind": "artifact",
      "level": "focused CI-like",
      "value": "marketing-gitops-promotion-main-3bb808e43605.zip"
    },
    {
      "kind": "db-migration",
      "level": "live DB",
      "value": "applied"
    },
    {
      "kind": "db-query",
      "level": "live DB",
      "value": "row-evidence"
    }
  ]
}