[
  {
    "id": "todo_1782543676384",
    "content": "Build codetether-worker image from local source",
    "status": "pending",
    "priority": "high",
    "created_at": "2026-06-27T07:01:16.384700619+00:00"
  },
  {
    "id": "todo_1782543676385",
    "content": "Push image to Artifact Registry (latest + dated tag)",
    "status": "pending",
    "priority": "high",
    "created_at": "2026-06-27T07:01:16.385816841+00:00"
  },
  {
    "id": "todo_1782543676386",
    "content": "Roll harvester StatefulSet and verify",
    "status": "done",
    "priority": "high",
    "created_at": "2026-06-27T07:01:16.386907211+00:00"
  }
]